nat/meta/pypi.md
nat/plugins/autogen/__init__.py
nat/plugins/autogen/callback_handler.py
nat/plugins/autogen/llm.py
nat/plugins/autogen/register.py
nat/plugins/autogen/tool_wrapper.py
nvidia_nat_autogen-1.5.0a20260130.dist-info/licenses/LICENSE-3rd-party.txt
nvidia_nat_autogen-1.5.0a20260130.dist-info/licenses/LICENSE.md
nvidia_nat_autogen-1.5.0a20260130.dist-info/METADATA
nvidia_nat_autogen-1.5.0a20260130.dist-info/WHEEL
nvidia_nat_autogen-1.5.0a20260130.dist-info/entry_points.txt
nvidia_nat_autogen-1.5.0a20260130.dist-info/top_level.txt
nvidia_nat_autogen-1.5.0a20260130.dist-info/RECORD
