Metadata-Version: 2.4
Name: nvidia-nat-autogen
Version: 1.5.0a20260130
Summary: Subpackage for AutoGen integration in NeMo Agent toolkit
Project-URL: documentation, https://docs.nvidia.com/nemo/agent-toolkit/latest/
Project-URL: source, https://github.com/NVIDIA/NeMo-Agent-Toolkit
Keywords: ai,agents,autogen,multi-agent
Classifier: Programming Language :: Python
Classifier: Programming Language :: Python :: 3.11
Classifier: Programming Language :: Python :: 3.12
Classifier: Programming Language :: Python :: 3.13
Requires-Python: <3.14,>=3.11
License-File: LICENSE-3rd-party.txt
License-File: LICENSE.md
Requires-Dist: autogen-agentchat~=0.7
Requires-Dist: autogen-core~=0.7
Requires-Dist: autogen-ext[anthropic]~=0.7
Requires-Dist: nvidia-nat==v1.5.0a20260130
Dynamic: license-file
